MANIFEST.in
README.md
setup.py
majorityredis/__init__.py
majorityredis/api.py
majorityredis/configure_logging.py
majorityredis/exceptions.py
majorityredis/getset.py
majorityredis/lock.py
majorityredis/lockingqueue.py
majorityredis/util.py
majorityredis.egg-info/PKG-INFO
majorityredis.egg-info/SOURCES.txt
majorityredis.egg-info/dependency_links.txt
majorityredis.egg-info/requires.txt
majorityredis.egg-info/top_level.txt