Metadata-Version: 1.0
Name: majorityredis
Version: 0.1
Summary: Distributed consensus algorithms and client-side API to work with N independent Redis Servers. WARNING: BETA!
Home-page: https://github.com/adgaudio/majorityredis
Author: Alex Gaudio
Author-email: agaudio@sailthru.com
License: UNKNOWN
Keywords: Redis,CAP,Brewer's Theorem,Majority,Consensus,api
Platform: UNKNOWN
